setup.py
t_daemon/__init__.py
t_daemon/daemon.py
t_daemon/service.py
t_daemon.egg-info/PKG-INFO
t_daemon.egg-info/SOURCES.txt
t_daemon.egg-info/dependency_links.txt
t_daemon.egg-info/requires.txt
t_daemon.egg-info/top_level.txt
t_daemon.egg-info/zip-safe