Metadata-Version: 1.0
Name: t-daemon
Version: 0.1
Summary: T daemon library
Home-page: https://gitlab.com/ddmello/lib/python/t_daemon.git
Author: Darrin D'Mello
Author-email: darrin.dmello@gmail.com
License: MIT
Platform: UNKNOWN
